odoo/addons/partner_socialmedia/README.rst
odoo/addons/partner_socialmedia/__init__.py
odoo/addons/partner_socialmedia/__manifest__.py
odoo/addons/partner_socialmedia/i18n/partner_socialmedia.pot
odoo/addons/partner_socialmedia/models/__init__.py
odoo/addons/partner_socialmedia/models/res_partner.py
odoo/addons/partner_socialmedia/static/description/icon.png
odoo/addons/partner_socialmedia/views/res_partner_view.xml
odoo12_addon_partner_socialmedia-12.0.1.0.1.dist-info/METADATA
odoo12_addon_partner_socialmedia-12.0.1.0.1.dist-info/WHEEL
odoo12_addon_partner_socialmedia-12.0.1.0.1.dist-info/top_level.txt
odoo12_addon_partner_socialmedia-12.0.1.0.1.dist-info/RECORD
